{
  "fill" : {
    "linear-gradient" : [
      "extended-gray:1.00000,1.00000",
      "display-p3:0.64095,0.65501,0.66125,1.00000"
    ],
    "orientation" : {
      "start" : {
        "x" : 0.5,
        "y" : 1
      },
      "stop" : {
        "x" : 0.5,
        "y" : 0.3
      }
    }
  },
  "groups" : [
    {
      "blur-material" : 0.48,
      "layers" : [
        {
          "image-name" : "CC2.png",
          "name" : "CC2",
          "position" : {
            "scale" : 1.09,
            "translation-in-points" : [
              0,
              0
            ]
          }
        }
      ],
      "lighting" : "individual",
      "position" : {
        "scale" : 0.89,
        "translation-in-points" : [
          -11,
          0
        ]
      },
      "shadow" : {
        "kind" : "layer-color",
        "opacity" : 0.88
      },
      "specular" : true,
      "translucency" : {
        "enabled" : true,
        "value" : 0.42
      }
    }
  ],
  "supported-platforms" : {
    "circles" : [
      "watchOS"
    ],
    "squares" : "shared"
  }
}